{
    "base": {
        "id": 1,
        "drive_mode": 0,
        "homing_offset": 225,
        "range_min": 1041,
        "range_max": 3101
    },
    "link3": {
        "id": 6,
        "drive_mode": 0,
        "homing_offset": -909,
        "range_min": 212,
        "range_max": 3993
    },
    "link4": {
        "id": 7,
        "drive_mode": 0,
        "homing_offset": -1240,
        "range_min": 864,
        "range_max": 3225
    },
    "link5": {
        "id": 8,
        "drive_mode": 0,
        "homing_offset": -1459,
        "range_min": 418,
        "range_max": 3934
    },
    "gripper": {
        "id": 9,
        "drive_mode": 0,
        "homing_offset": 1347,
        "range_min": 400,
        "range_max": 2131
    },
    "link1_follower": {
        "id": 3,
        "drive_mode": 0,
        "homing_offset": 100,
        "range_min": 720,
        "range_max": 3300
    },
    "link2_follower": {
        "id": 5,
        "drive_mode": 0,
        "homing_offset": 95,
        "range_min": 821,
        "range_max": 3085
    },
    "link1": {
        "id": 2,
        "drive_mode": 0,
        "homing_offset": 68,
        "range_min": 804,
        "range_max": 3376
    },
    "link2": {
        "id": 4,
        "drive_mode": 0,
        "homing_offset": 54,
        "range_min": 1016,
        "range_max": 3279
    }
}